pelican/plugins/figures/__init__.py
pelican/plugins/figures/extension.py
pelican/plugins/figures/figures.py
pelican/plugins/figures/markdown_extension.py
pelican/plugins/figures/test_figures.py
pelican_figures-0.1.0.dist-info/WHEEL
pelican_figures-0.1.0.dist-info/METADATA
pelican_figures-0.1.0.dist-info/RECORD
